{
  "id": "211e2d74-4f9d-46eb-bad5-d5c26a28f695",
  "prevId": "00000000-0000-0000-0000-000000000000",
  "version": "7",
  "dialect": "postgresql",
  "tables": {
    "public.events": {
      "name": "events",
      "schema": "",
      "columns": {
        "id": {
          "name": "id",
          "type": "serial",
          "primaryKey": true,
          "notNull": true
        },
        "title": {
          "name": "title",
          "type": "text",
          "primaryKey": false,
          "notNull": true
        },
        "description": {
          "name": "description",
          "type": "text",
          "primaryKey": false,
          "notNull": false
        },
        "date": {
          "name": "date",
          "type": "timestamp",
          "primaryKey": false,
          "notNull": true
        },
        "location": {
          "name": "location",
          "type": "text",
          "primaryKey": false,
          "notNull": false
        },
        "image": {
          "name": "image",
          "type": "text",
          "primaryKey": false,
          "notNull": false
        },
        "published": {
          "name": "published",
          "type": "boolean",
          "primaryKey": false,
          "notNull": true,
          "default": false
        },
        "created_at": {
          "name": "created_at",
          "type": "timestamp",
          "primaryKey": false,
          "notNull": false,
          "default": "now()"
        },
        "updated_at": {
          "name": "updated_at",
          "type": "timestamp",
          "primaryKey": false,
          "notNull": false,
          "default": "now()"
        }
      },
      "indexes": {},
      "foreignKeys": {},
      "compositePrimaryKeys": {},
      "uniqueConstraints": {},
      "policies": {},
      "checkConstraints": {},
      "isRLSEnabled": false
    },
    "public.performance_test_results": {
      "name": "performance_test_results",
      "schema": "",
      "columns": {
        "id": {
          "name": "id",
          "type": "serial",
          "primaryKey": true,
          "notNull": true
        },
        "test_id": {
          "name": "test_id",
          "type": "integer",
          "primaryKey": false,
          "notNull": true
        },
        "device_name": {
          "name": "device_name",
          "type": "text",
          "primaryKey": false,
          "notNull": true
        },
        "browser_name": {
          "name": "browser_name",
          "type": "text",
          "primaryKey": false,
          "notNull": true
        },
        "platform": {
          "name": "platform",
          "type": "text",
          "primaryKey": false,
          "notNull": true
        },
        "page": {
          "name": "page",
          "type": "text",
          "primaryKey": false,
          "notNull": true
        },
        "load_time": {
          "name": "load_time",
          "type": "real",
          "primaryKey": false,
          "notNull": true
        },
        "dom_content_loaded": {
          "name": "dom_content_loaded",
          "type": "real",
          "primaryKey": false,
          "notNull": false
        },
        "first_paint": {
          "name": "first_paint",
          "type": "real",
          "primaryKey": false,
          "notNull": false
        },
        "success": {
          "name": "success",
          "type": "boolean",
          "primaryKey": false,
          "notNull": true
        },
        "error": {
          "name": "error",
          "type": "text",
          "primaryKey": false,
          "notNull": false
        },
        "page_title": {
          "name": "page_title",
          "type": "text",
          "primaryKey": false,
          "notNull": false
        },
        "created_at": {
          "name": "created_at",
          "type": "timestamp",
          "primaryKey": false,
          "notNull": false,
          "default": "now()"
        }
      },
      "indexes": {},
      "foreignKeys": {
        "performance_test_results_test_id_performance_tests_id_fk": {
          "name": "performance_test_results_test_id_performance_tests_id_fk",
          "tableFrom": "performance_test_results",
          "tableTo": "performance_tests",
          "columnsFrom": [
            "test_id"
          ],
          "columnsTo": [
            "id"
          ],
          "onDelete": "no action",
          "onUpdate": "no action"
        }
      },
      "compositePrimaryKeys": {},
      "uniqueConstraints": {},
      "policies": {},
      "checkConstraints": {},
      "isRLSEnabled": false
    },
    "public.performance_tests": {
      "name": "performance_tests",
      "schema": "",
      "columns": {
        "id": {
          "name": "id",
          "type": "serial",
          "primaryKey": true,
          "notNull": true
        },
        "test_date": {
          "name": "test_date",
          "type": "timestamp",
          "primaryKey": false,
          "notNull": true,
          "default": "now()"
        },
        "total_tests": {
          "name": "total_tests",
          "type": "integer",
          "primaryKey": false,
          "notNull": true
        },
        "successful_tests": {
          "name": "successful_tests",
          "type": "integer",
          "primaryKey": false,
          "notNull": true
        },
        "failed_tests": {
          "name": "failed_tests",
          "type": "integer",
          "primaryKey": false,
          "notNull": true
        },
        "success_rate": {
          "name": "success_rate",
          "type": "real",
          "primaryKey": false,
          "notNull": true
        },
        "avg_load_time": {
          "name": "avg_load_time",
          "type": "real",
          "primaryKey": false,
          "notNull": true
        },
        "min_load_time": {
          "name": "min_load_time",
          "type": "real",
          "primaryKey": false,
          "notNull": false
        },
        "max_load_time": {
          "name": "max_load_time",
          "type": "real",
          "primaryKey": false,
          "notNull": false
        },
        "duration": {
          "name": "duration",
          "type": "real",
          "primaryKey": false,
          "notNull": true
        },
        "status": {
          "name": "status",
          "type": "text",
          "primaryKey": false,
          "notNull": true,
          "default": "'running'"
        },
        "results": {
          "name": "results",
          "type": "jsonb",
          "primaryKey": false,
          "notNull": false
        },
        "created_at": {
          "name": "created_at",
          "type": "timestamp",
          "primaryKey": false,
          "notNull": false,
          "default": "now()"
        }
      },
      "indexes": {},
      "foreignKeys": {},
      "compositePrimaryKeys": {},
      "uniqueConstraints": {},
      "policies": {},
      "checkConstraints": {},
      "isRLSEnabled": false
    },
    "public.posts": {
      "name": "posts",
      "schema": "",
      "columns": {
        "id": {
          "name": "id",
          "type": "serial",
          "primaryKey": true,
          "notNull": true
        },
        "title": {
          "name": "title",
          "type": "text",
          "primaryKey": false,
          "notNull": true
        },
        "slug": {
          "name": "slug",
          "type": "text",
          "primaryKey": false,
          "notNull": true
        },
        "content": {
          "name": "content",
          "type": "text",
          "primaryKey": false,
          "notNull": true
        },
        "excerpt": {
          "name": "excerpt",
          "type": "text",
          "primaryKey": false,
          "notNull": false
        },
        "type": {
          "name": "type",
          "type": "text",
          "primaryKey": false,
          "notNull": true,
          "default": "'blog'"
        },
        "published": {
          "name": "published",
          "type": "boolean",
          "primaryKey": false,
          "notNull": false,
          "default": false
        },
        "author_id": {
          "name": "author_id",
          "type": "integer",
          "primaryKey": false,
          "notNull": false
        },
        "created_at": {
          "name": "created_at",
          "type": "timestamp",
          "primaryKey": false,
          "notNull": false,
          "default": "now()"
        },
        "updated_at": {
          "name": "updated_at",
          "type": "timestamp",
          "primaryKey": false,
          "notNull": false,
          "default": "now()"
        }
      },
      "indexes": {},
      "foreignKeys": {
        "posts_author_id_users_id_fk": {
          "name": "posts_author_id_users_id_fk",
          "tableFrom": "posts",
          "tableTo": "users",
          "columnsFrom": [
            "author_id"
          ],
          "columnsTo": [
            "id"
          ],
          "onDelete": "no action",
          "onUpdate": "no action"
        }
      },
      "compositePrimaryKeys": {},
      "uniqueConstraints": {
        "posts_slug_unique": {
          "name": "posts_slug_unique",
          "nullsNotDistinct": false,
          "columns": [
            "slug"
          ]
        }
      },
      "policies": {},
      "checkConstraints": {},
      "isRLSEnabled": false
    },
    "public.ticket_types": {
      "name": "ticket_types",
      "schema": "",
      "columns": {
        "id": {
          "name": "id",
          "type": "serial",
          "primaryKey": true,
          "notNull": true
        },
        "name": {
          "name": "name",
          "type": "text",
          "primaryKey": false,
          "notNull": true
        },
        "price": {
          "name": "price",
          "type": "integer",
          "primaryKey": false,
          "notNull": true,
          "default": 0
        },
        "description": {
          "name": "description",
          "type": "text",
          "primaryKey": false,
          "notNull": false
        },
        "created_at": {
          "name": "created_at",
          "type": "timestamp",
          "primaryKey": false,
          "notNull": false,
          "default": "now()"
        },
        "updated_at": {
          "name": "updated_at",
          "type": "timestamp",
          "primaryKey": false,
          "notNull": false,
          "default": "now()"
        }
      },
      "indexes": {},
      "foreignKeys": {},
      "compositePrimaryKeys": {},
      "uniqueConstraints": {},
      "policies": {},
      "checkConstraints": {},
      "isRLSEnabled": false
    },
    "public.tickets": {
      "name": "tickets",
      "schema": "",
      "columns": {
        "id": {
          "name": "id",
          "type": "serial",
          "primaryKey": true,
          "notNull": true
        },
        "event_id": {
          "name": "event_id",
          "type": "integer",
          "primaryKey": false,
          "notNull": true
        },
        "participant_name": {
          "name": "participant_name",
          "type": "text",
          "primaryKey": false,
          "notNull": true
        },
        "participant_email": {
          "name": "participant_email",
          "type": "text",
          "primaryKey": false,
          "notNull": true
        },
        "ticket_type": {
          "name": "ticket_type",
          "type": "text",
          "primaryKey": false,
          "notNull": true,
          "default": "'standard'"
        },
        "price_paid": {
          "name": "price_paid",
          "type": "integer",
          "primaryKey": false,
          "notNull": true,
          "default": 0
        },
        "ticket_code": {
          "name": "ticket_code",
          "type": "text",
          "primaryKey": false,
          "notNull": true
        },
        "status": {
          "name": "status",
          "type": "text",
          "primaryKey": false,
          "notNull": true,
          "default": "'valid'"
        },
        "scanned_at": {
          "name": "scanned_at",
          "type": "timestamp",
          "primaryKey": false,
          "notNull": false
        },
        "scanned_by": {
          "name": "scanned_by",
          "type": "integer",
          "primaryKey": false,
          "notNull": false
        },
        "issued_by": {
          "name": "issued_by",
          "type": "integer",
          "primaryKey": false,
          "notNull": false
        },
        "created_at": {
          "name": "created_at",
          "type": "timestamp",
          "primaryKey": false,
          "notNull": false,
          "default": "now()"
        },
        "updated_at": {
          "name": "updated_at",
          "type": "timestamp",
          "primaryKey": false,
          "notNull": false,
          "default": "now()"
        }
      },
      "indexes": {},
      "foreignKeys": {
        "tickets_event_id_events_id_fk": {
          "name": "tickets_event_id_events_id_fk",
          "tableFrom": "tickets",
          "tableTo": "events",
          "columnsFrom": [
            "event_id"
          ],
          "columnsTo": [
            "id"
          ],
          "onDelete": "no action",
          "onUpdate": "no action"
        },
        "tickets_scanned_by_users_id_fk": {
          "name": "tickets_scanned_by_users_id_fk",
          "tableFrom": "tickets",
          "tableTo": "users",
          "columnsFrom": [
            "scanned_by"
          ],
          "columnsTo": [
            "id"
          ],
          "onDelete": "no action",
          "onUpdate": "no action"
        },
        "tickets_issued_by_users_id_fk": {
          "name": "tickets_issued_by_users_id_fk",
          "tableFrom": "tickets",
          "tableTo": "users",
          "columnsFrom": [
            "issued_by"
          ],
          "columnsTo": [
            "id"
          ],
          "onDelete": "no action",
          "onUpdate": "no action"
        }
      },
      "compositePrimaryKeys": {},
      "uniqueConstraints": {
        "tickets_ticket_code_unique": {
          "name": "tickets_ticket_code_unique",
          "nullsNotDistinct": false,
          "columns": [
            "ticket_code"
          ]
        }
      },
      "policies": {},
      "checkConstraints": {},
      "isRLSEnabled": false
    },
    "public.users": {
      "name": "users",
      "schema": "",
      "columns": {
        "id": {
          "name": "id",
          "type": "serial",
          "primaryKey": true,
          "notNull": true
        },
        "email": {
          "name": "email",
          "type": "text",
          "primaryKey": false,
          "notNull": true
        },
        "password_hash": {
          "name": "password_hash",
          "type": "text",
          "primaryKey": false,
          "notNull": true
        },
        "name": {
          "name": "name",
          "type": "text",
          "primaryKey": false,
          "notNull": false
        },
        "role": {
          "name": "role",
          "type": "text",
          "primaryKey": false,
          "notNull": true,
          "default": "'admin'"
        },
        "active": {
          "name": "active",
          "type": "boolean",
          "primaryKey": false,
          "notNull": false,
          "default": true
        },
        "created_at": {
          "name": "created_at",
          "type": "timestamp",
          "primaryKey": false,
          "notNull": false,
          "default": "now()"
        }
      },
      "indexes": {},
      "foreignKeys": {},
      "compositePrimaryKeys": {},
      "uniqueConstraints": {
        "users_email_unique": {
          "name": "users_email_unique",
          "nullsNotDistinct": false,
          "columns": [
            "email"
          ]
        }
      },
      "policies": {},
      "checkConstraints": {},
      "isRLSEnabled": false
    }
  },
  "enums": {},
  "schemas": {},
  "sequences": {},
  "roles": {},
  "policies": {},
  "views": {},
  "_meta": {
    "columns": {},
    "schemas": {},
    "tables": {}
  }
}